ai_toolkit/__init__.py
ai_toolkit/ai_service.py
ai_toolkit/cli.py
ai_toolkit/config_manager.py
ai_toolkit/git_utils.py
ai_toolkit/setup.py
ai_toolkit/ui_utils.py
ai_toolkit/utils.py
git_ai_toolkit-0.2.5.dist-info/LICENSE.txt
git_ai_toolkit-0.2.5.dist-info/METADATA
git_ai_toolkit-0.2.5.dist-info/WHEEL
git_ai_toolkit-0.2.5.dist-info/entry_points.txt
git_ai_toolkit-0.2.5.dist-info/top_level.txt
git_ai_toolkit-0.2.5.dist-info/RECORD
