Metadata-Version: 2.1
Name: git-ai-toolkit
Version: 0.2.5
Summary: A toolkit for using OpenAI's GPT-4o-mini model to assist with Git workflows.
Home-page: https://github.com/maximilianlemberg-awl/git-ai-toolkit
Author: Maximilian Lemberg
License: MIT
Classifier: Programming Language :: Python :: 3
Classifier: License :: OSI Approved :: MIT License
Classifier: Operating System :: OS Independent
Requires-Python: >=3.9
License-File: LICENSE.txt
Requires-Dist: openai>=1.79.0
Requires-Dist: colorama>=0.4.6
